coinbase_agentkit_strands_agents/__init__.py
coinbase_agentkit_strands_agents/strands_agents_tools.py
coinbase_agentkit_strands_agents-0.2.0.dist-info/METADATA
coinbase_agentkit_strands_agents-0.2.0.dist-info/WHEEL
coinbase_agentkit_strands_agents-0.2.0.dist-info/RECORD
