Metadata-Version: 2.4
Name: coinbase-agentkit-strands-agents
Version: 0.2.0
Summary: Coinbase AgentKit Strands Agents extension
Author-email: Uchenna Egbe <ucheegbe@amazon.com>
License-Expression: Apache-2.0
Keywords: agent,agentkit,ai,cdp,coinbase,crypto,sdk,strands,strands agents
Requires-Python: ~=3.10
Requires-Dist: coinbase-agentkit<0.8,>=0.7.2
Requires-Dist: nest-asyncio<2,>=1.5.8
Requires-Dist: python-dotenv<2,>=1.0.1
Requires-Dist: strands-agents-builder>=0.1.7
Requires-Dist: strands-agents-tools>=0.2.1
Requires-Dist: strands-agents>=1.0.1
